Workbook

Sheet ERP_Cleaned
A1: RAW_PO_NUMBER | B1: TRANSACTION_DATE | C1: DEPARTMENT_NAME | D1: EXPENSE_CATEGORY | E1: VENDOR_NAME | F1: RAW_AMOUNT | G1: GL_CODE | H1: TAX_RATE | I1: APPROVAL_STATUS | J1: INVOICE_REF | K1: SYSTEM_COMMENTS
A2: PO-2024-2002 | B2: 45932 | C2: Facilities & Ops | D2: Travel & Entertainment | E2: Prime Space Realty | F2: 115160.76 | G2: GL-500100 | H2: 12% | I2: APPROVED | K2: System Auto-Generated
A3: PO-2024-2006 | B3: 45908 | C3: IT Operations | D3: Office Supplies | E3: CloudSaaS Corp | F3: 186051.69 | G3: GL-500100 | H3: 12% | I3: APPROVED | J3: INV-5166 | K3: System Auto-Generated
A4: PO-2024-2008 | B4: 45954 | C4: Marketing & Sales | D4: Digital Advertising | E4: PaperCorp Supplies | F4: 113149.23 | G4: GL-500200 | H4: 12% | I4: APPROVED | J4: INV-8892 | K4: Urgent operational requirement!
A5: PO-2024-2016 | B5: 45946 | C5: Facilities & Ops | D5: Office Supplies | E5: Prime Space Realty | F5: 206325.42 | G5: GL-500100 | H5: 12% | I5: APPROVED | J5: INV-8900 | K5: System Auto-Generated
A6: PO-2024-2017 | B6: 45069 | C6: IT Operations | D6: Digital Advertising | E6: CloudSaaS Corp | F6: 57783.36 | G6: GL-500100 | H6: 0% | I6: APPROVED | J6: INV-5544 | K6: System Auto-Generated
A7: PO-2024-2018 | B7: 44968 | C7: Marketing & Sales | D7: Office Rent | E7: Prime Space Realty | F7: 51244.28 | G7: GL-600300 | H7: 12% | I7: APPROVED | J7: INV-7194 | K7: Urgent operational requirement!
B8: 45117 | C8: Facilities & Ops | D8: Office Rent | E8: GlobalMedia Ads | F8: 92128.53 | G8: GL-600300 | H8: 12% | I8: APPROVED | J8: INV-8603 | K8: System Auto-Generated
A9: PO-2024-2023 | B9: 45467 | C9: IT Operations | D9: Digital Advertising | E9: TechDistributors Inc | F9: 36320.02 | G9: GL-500100 | H9: 12% | I9: APPROVED | K9: System Auto-Generated
A10: PO-2024-2026 | B10: 45004 | C10: Facilities & Ops | D10: Cloud Infrastructure | E10: Prime Space Realty | F10: 50577.43 | G10: GL-500200 | H10: 12% | I10: APPROVED | J10: INV-9582 | K10: System Auto-Generated
A11: PO-2024-2027 | B11: 45442 | C11: Facilities & Ops | D11: Cloud Infrastructure | E11: GlobalMedia Ads | F11: 17764.09 | G11: GL-600300 | H11: 12% | I11: APPROVED | J11: INV-9956 | K11: System Auto-Generated
A12: PO-2024-2030 | B12: 45699 | C12: Marketing & Sales | D12: Travel & Entertainment | E12: PaperCorp Supplies | F12: 170659.31 | G12: GL-500100 | H12: 12% | I12: APPROVED | J12: INV-9601 | K12: System Auto-Generated
A13: PO-2024-2035 | B13: 45767 | C13: Marketing & Sales | D13: Digital Advertising | E13: CloudSaaS Corporation | F13: 242782.85 | G13: GL-600300 | H13: 12% | I13: APPROVED | K13: System Auto-Generated
A14: PO-2024-2040 | B14: 44931 | C14: Facilities & Ops | D14: Cloud Infrastructure | E14: CloudSaaS Corp | F14: 83487.25 | G14: GL-500100 | H14: 12% | I14: APPROVED | J14: INV-7969 | K14: Urgent operational requirement!
A15: PO-2024-2044 | B15: 45640 | C15: Facilities & Ops | D15: Travel & Entertainment | E15: GlobalMedia Ads | F15: 134858 | G15: GL-600300 | H15: 12% | I15: APPROVED | J15: INV-5045 | K15: System Auto-Generated
A16: PO-2024-2050 | B16: 44950 | C16: Unassigned | D16: Hardware Procurement | E16: GlobalMedia Ads | F16: 214019.64 | G16: GL-500200 | H16: 12% | I16: APPROVED | K16: System Auto-Generated
A17: PO-2024-2055 | B17: 45592 | C17: Facilities & Ops | D17: Cloud Infrastructure | E17: GlobalMedia Ads | F17: 88319.3 | G17: GL-500100 | H17: 12% | I17: APPROVED | J17: INV-8325 | K17: System Auto-Generated
A18: PO-2024-2056 | B18: 45711 | C18: Marketing & Sales | D18: Software Licenses | E18: Prime Space Realty | F18: 250076.66 | G18: GL-500100 | H18: 12% | I18: APPROVED | J18: INV-5036 | K18: System Auto-Generated
A19: PO-2024-2058 | B19: 45314 | C19: Marketing & Sales | D19: Office Supplies | E19: Prime Space Realty | F19: 168739.9 | G19: GL-500100 | H19: 12% | I19: APPROVED | J19: INV-8693 | K19: System Auto-Generated
A20: PO-2024-2060 | B20: 45307 | C20: Marketing & Sales | D20: Hardware Procurement | E20: PaperCorp Supplies | F20: 153905 | G20: GL-500200 | H20: 12% | I20: APPROVED | J20: INV-8446 | K20: System Auto-Generated
A21: PO-2024-2061 | B21: 45760 | C21: Marketing & Sales | D21: Cloud Infrastructure | E21: TechDistributors Inc | F21: 183744.55 | G21: GL-500100 | H21: 12% | I21: APPROVED | J21: INV-9772 | K21: Urgent operational requirement!
A22: PO-2024-2062 | B22: 45453 | C22: HR & Admin | D22: Travel & Entertainment | E22: CloudSaaS Corp | F22: 42533.69 | G22: GL-500100 | H22: 12% | I22: APPROVED | J22: INV-5398 | K22: System Auto-Generated
A23: PO-2024-2064 | B23: 45829 | C23: IT Operations | D23: Office Supplies | E23: PaperCorp Supplies | F23: 34540.36 | G23: GL-500100 | H23: 12% | I23: APPROVED | J23: INV-9562 | K23: System Auto-Generated
A24: PO-2024-2067 | B24: 45221 | C24: IT Operations | D24: Hardware Procurement | E24: GlobalMedia Ads | F24: 128124.55 | G24: GL-600300 | H24: 12% | I24: APPROVED | J24: INV-6672 | K24: System Auto-Generated
A25: PO-2024-2068 | B25: 45088 | C25: Facilities & Ops | D25: Digital Advertising | E25: GlobalMedia Ads | F25: 121957.05 | G25: GL-600300 | H25: 12% | I25: APPROVED | J25: INV-4659 | K25: System Auto-Generated
A26: PO-2024-2070 | B26: 45202 | C26: IT Operations | D26: Software Licenses | E26: PaperCorp Supplies | F26: 29801.85 | G26: GL-600300 | H26: 12% | I26: APPROVED | J26: INV-4582 | K26: System Auto-Generated
A27: PO-2024-2071 | B27: 45993 | C27: IT Operations | D27: Office Rent | E27: GlobalMedia Ads | F27: 311092.01 | G27: GL-500200 | H27: 12% | I27: APPROVED | J27: INV-9656 | K27: System Auto-Generated
A28: PO-2024-2072 | B28: 45415 | C28: IT Operations | D28: Travel & Entertainment | E28: GlobalMedia Ads | F28: 127541.66 | G28: GL-500200 | H28: 12% | I28: APPROVED | J28: INV-8819 | K28: System Auto-Generated
... A30: PO-2024-2074 | B30: 45994 | C30: HR & Admin | D30: Cloud Infrastructure | E30: PaperCorp Supplies | F30: 298392.91 | G30: GL-600300 | H30: 0% | I30: APPROVED | J30: INV-7018 | K30: System Auto-Generated
A31: PO-2024-2076 | B31: 45464 | C31: Facilities & Ops | D31: Travel & Entertainment | E31: TechDistributors Inc | F31: 126727.01 | G31: GL-500200 | H31: 0% | I31: APPROVED | K31: System Auto-Generated
A32: PO-2024-2077 | B32: 45163 | C32: Facilities & Ops | D32: Office Supplies | E32: CloudSaaS Corporation | F32: 80824.49 | G32: GL-600300 | H32: 12% | I32: APPROVED | J32: INV-5556 | K32: System Auto-Generated
A33: PO-2024-2078 | B33: 45913 | C33: IT Operations | D33: Cloud Infrastructure | E33: CloudSaaS Corp | F33: 58524.65 | G33: GL-500100 | H33: 12% | I33: APPROVED | J33: INV-7861 | K33: System Auto-Generated
A34: PO-2024-2079 | B34: 45073 | C34: Marketing & Sales | D34: Office Rent | E34: Prime Space Realty | F34: 40200.79 | G34: GL-600300 | H34: 12% | I34: APPROVED | K34: System Auto-Generated
A35: PO-2024-2080 | B35: 45731 | C35: Facilities & Ops | D35: Software Licenses | E35: TechDistributors Inc | F35: 12518.53 | G35: GL-500200 | H35: 12% | I35: APPROVED | J35: INV-5405 | K35: System Auto-Generated
A36: PO-2024-2084 | B36: 45414 | C36: IT Operations | D36: Digital Advertising | E36: TechDistributors Inc | F36: 280488.2 | G36: GL-600300 | H36: 12% | I36: APPROVED | J36: INV-4233 | K36: System Auto-Generated
A37: PO-2024-2085 | B37: 45286 | C37: Marketing & Sales | D37: Digital Advertising | E37: Prime Space Realty | F37: 33710.14 | G37: GL-600300 | H37: 12% | I37: APPROVED | J37: INV-9424 | K37: System Auto-Generated
A38: PO-2024-2087 | B38: 44937 | C38: Facilities & Ops | D38: Office Supplies | E38: CloudSaaS Corp | F38: 24786.39 | G38: GL-500200 | H38: 12% | I38: APPROVED | J38: INV-7594 | K38: System Auto-Generated
A39: PO-2024-2088 | B39: 45536 | C39: HR & Admin | D39: Digital Advertising | E39: Prime Space Realty | F39: 100068 | G39: GL-500200 | H39: 12% | I39: APPROVED | J39: INV-5675 | K39: Urgent operational requirement!
A40: PO-2024-2089 | B40: 45530 | C40: Marketing & Sales | D40: Travel & Entertainment | E40: PaperCorp Supplies | F40: 56772.71 | G40: GL-600300 | H40: 12% | I40: APPROVED | J40: INV-5052 | K40: System Auto-Generated
A41: PO-2024-2095 | B41: 45367 | C41: Marketing & Sales | D41: Digital Advertising | E41: Prime Space Realty | F41: 96138.43 | G41: GL-500100 | H41: 12% | I41: APPROVED | J41: INV-4831 | K41: System Auto-Generated
A42: PO-2024-2096 | B42: 45741 | C42: IT Operations | D42: Digital Advertising | E42: Prime Space Realty | F42: 114483.44 | G42: GL-600300 | H42: 12% | I42: APPROVED | J42: INV-4028 | K42: System Auto-Generated
A43: PO-2024-2097 | B43: 45062 | C43: Facilities & Ops | D43: Cloud Infrastructure | E43: TechDistributors Inc | F43: 103560.67 | G43: GL-500200 | H43: 0% | I43: APPROVED | J43: INV-8542 | K43: System Auto-Generated
A44: PO-2024-2099 | B44: 45794 | C44: Facilities & Ops | D44: Hardware Procurement | E44: CloudSaaS Corp | F44: 9799.7 | G44: GL-500200 | H44: 12% | I44: APPROVED | K44: System Auto-Generated
A45: PO-2024-2100 | B45: 45128 | C45: Unassigned | D45: Digital Advertising | E45: TechDistributors Inc | F45: 96480.34 | G45: GL-500100 | H45: 12% | I45: APPROVED | J45: INV-5383 | K45: System Auto-Generated
B46: 45217 | C46: IT Operations | D46: Office Supplies | E46: GlobalMedia Ads | F46: 74694.26 | G46: GL-500200 | H46: 12% | I46: APPROVED | J46: INV-7362 | K46: System Auto-Generated
A47: PO-2024-2104 | B47: 45831 | C47: Marketing & Sales | D47: Cloud Infrastructure | E47: Prime Space Realty | F47: 82054.02 | G47: GL-500200 | H47: 12% | I47: APPROVED | J47: INV-8873 | K47: Urgent operational requirement!
A48: PO-2024-2106 | B48: 45808 | C48: Facilities & Ops | D48: Office Rent | E48: PaperCorp Supplies | F48: 151054.99 | G48: GL-600300 | H48: 12% | I48: APPROVED | J48: INV-6873 | K48: System Auto-Generated
A49: PO-2024-2108 | B49: 45604 | C49: Facilities & Ops | D49: Cloud Infrastructure | E49: PaperCorp Supplies | F49: 74311.54 | G49: GL-600300 | H49: 12% | I49: APPROVED | K49: Urgent operational requirement!
A50: PO-2024-2109 | B50: 45678 | C50: Facilities & Ops | D50: Office Supplies | E50: Prime Space Realty | F50: 118928.53 | G50: GL-600300 | H50: 12% | I50: APPROVED | K50: System Auto-Generated
A51: PO-2024-2111 | B51: 45514 | C51: Facilities & Ops | D51: Cloud Infrastructure | E51: Prime Space Realty | F51: 162114.29 | G51: GL-500200 | H51: 12% | I51: APPROVED | J51: INV-9239 | K51: System Auto-Generated
A52: PO-2024-2113 | B52: 45120 | C52: Facilities & Ops | D52: Hardware Procurement | E52: PaperCorp Supplies | F52: 45405.73 | G52: GL-600300 | H52: 12% | I52: APPROVED | J52: INV-9650 | K52: Urgent operational requirement!
A53: PO-2024-2114 | B53: 45138 | C53: Marketing & Sales | D53: Digital Advertising | E53: PaperCorp Supplies | F53: 20644.86 | G53: GL-500200 | H53: 12% | I53: APPROVED | J53: INV-6264 | K53: System Auto-Generated
A54: PO-2024-2115 | B54: 45325 | C54: HR & Admin | D54: Cloud Infrastructure | E54: CloudSaaS Corp | F54: 75152.01 | G54: GL-600300 | H54: 0% | I54: APPROVED | J54: INV-6848 | K54: System Auto-Generated
A55: PO-2024-2118 | B55: 45633 | C55: Facilities & Ops | D55: Hardware Procurement | E55: GlobalMedia Ads | F55: 155027.88 | G55: GL-500100 | H55: 12% | I55: APPROVED | J55: INV-9846 | K55: System Auto-Generated
A56: PO-2024-2119 | B56: 45555 | C56: IT Operations | D56: Cloud Infrastructure | E56: PaperCorp Supplies | F56: 26349 | G56: GL-500200 | H56: 12% | I56: APPROVED | J56: INV-4387 | K56: System Auto-Generated
A57: PO-2024-2120 | B57: 45523 | C57: Facilities & Ops | D57: Digital Advertising | E57: CloudSaaS Corp | F57: 208702.47 | G57: GL-600300 | H57: 12% | I57: APPROVED | J57: INV-4227 | K57: Urgent operational requirement!
A58: PO-2024-2121 | B58: 45579 | C58: IT Operations | D58: Cloud Infrastructure | E58: Paper Corp | F58: 290788.1 | G58: GL-500200 | H58: 12% | I58: APPROVED | J58: INV-8717 | K58: Urgent operational requirement!
A59: PO-2024-2122 | B59: 45927 | C59: Marketing & Sales | D59: Digital Advertising | E59: CloudSaaS Corp | F59: 161329.22 | G59: GL-500200 | H59: 12% | I59: APPROVED | J59: INV-9193 | K59: System Auto-Generated
A60: PO-2024-2123 | B60: 45751 | C60: IT Operations | D60: Travel & Entertainment | E60: CloudSaaS Corp | F60: 205143.55 | G60: GL-500100 | H60: 12% | I60: APPROVED | K60: System Auto-Generated
A61: PO-2024-2125 | B61: 44945 | C61: Unassigned | D61: Software Licenses | E61: Prime Space Realty | F61: 106518.82 | G61: GL-500100 | H61: 12% | I61: APPROVED | J61: INV-6470 | K61: System Auto-Generated
A62: PO-2024-2129 | B62: 45521 | C62: Marketing & Sales | D62: Software Licenses | E62: CloudSaaS Corp | F62: 68677.67 | G62: GL-500200 | H62: 12% | I62: APPROVED | J62: INV-8186 | K62: System Auto-Generated
A63: PO-2024-2130 | B63: 45570 | C63: Facilities & Ops | D63: Software Licenses | E63: CloudSaaS Corp | G63: GL-500200 | H63: 0% | I63: APPROVED | J63: INV-6667 | K63: System Auto-Generated
A64: PO-2024-2131 | B64: 45577 | C64: Marketing & Sales | D64: Cloud Infrastructure | E64: Prime Space Realty | F64: 161409.7 | G64: GL-500100 | H64: 12% | I64: APPROVED | J64: INV-7940 | K64: System Auto-Generated
A65: PO-2024-2133 | B65: 45754 | C65: Facilities & Ops | D65: Office Supplies | E65: CloudSaaS Corporation | F65: 189712.64 | G65: GL-500100 | H65: 0% | I65: APPROVED | K65: System Auto-Generated
A66: PO-2024-2134 | B66: 45195 | C66: IT Operations | D66: Software Licenses | E66: PaperCorp Supplies | F66: 18866.32 | G66: GL-500100 | H66: 12% | I66: APPROVED | K66: System Auto-Generated
A67: PO-2024-2135 | B67: 45246 | C67: Facilities & Ops | D67: Hardware Procurement | E67: Tech Distributors | F67: 12378.79 | G67: GL-500200 | H67: 0% | I67: APPROVED | J67: INV-7911 | K67: System Auto-Generated
A68: PO-2024-2136 | B68: 46010 | C68: Marketing & Sales | D68: Travel & Entertainment | E68: CloudSaaS Corp | F68: 309478.17 | G68: GL-600300 | H68: 12% | I68: APPROVED | J68: INV-5952 | K68: System Auto-Generated
A69: PO-2024-2137 | B69: 45091 | C69: IT Operations | D69: Hardware Procurement | E69: CloudSaaS Corp | F69: 71238.41 | G69: GL-500100 | H69: 12% | I69: APPROVED | K69: System Auto-Generated
A70: PO-2024-2139 | B70: 45428 | C70: IT Operations | D70: Software Licenses | E70: TechDistributors Inc | F70: 127485.8 | G70: GL-500100 | H70: 12% | I70: APPROVED | J70: INV-7680 | K70: System Auto-Generated
A71: PO-2024-2140 | B71: 45621 | C71: Facilities & Ops | D71: Digital Advertising | E71: Prime Space Realty | F71: 172805.49 | G71: GL-600300 | H71: 12% | I71: APPROVED | J71: INV-4553 | K71: Urgent operational requirement!
A72: PO-2024-2141 | B72: 45316 | C72: Marketing & Sales | D72: Digital Advertising | E72: CloudSaaS Corp | F72: 200214.55 | G72: GL-500200 | H72: 12% | I72: APPROVED | J72: INV-8571 | K72: System Auto-Generated
A73: PO-2024-2142 | B73: 45204 | C73: Facilities & Ops | D73: Office Supplies | E73: Prime Space Realty | F73: 133396.25 | G73: GL-500200 | H73: 12% | I73: APPROVED | J73: INV-6791 | K73: System Auto-Generated
A74: PO-2024-2143 | B74: 45570 | C74: IT Operations | D74: Digital Advertising | E74: Paper Corp | F74: 287692.35 | G74: GL-500100 | H74: 12% | I74: APPROVED | J74: INV-8245 | K74: System Auto-Generated
A75: PO-2024-2146 | B75: 45283 | C75: IT Operations | D75: Office Supplies | E75: TechDistributors Inc | F75: 263422.4 | G75: GL-500200 | H75: 12% | I75: APPROVED | J75: INV-7305 | K75: Urgent operational requirement!
A76: PO-2024-2148 | B76: 45172 | C76: IT Operations | D76: Office Supplies | E76: Prime Space Realty | F76: 186069.28 | G76: GL-500200 | H76: 0% | I76: APPROVED | J76: INV-8390 | K76: System Auto-Generated
A77: PO-2024-2150 | B77: 45890 | C77: Unassigned | D77: Travel & Entertainment | E77: Tech Distributors | F77: 233987.98 | G77: GL-500200 | H77: 12% | I77: APPROVED | J77: INV-7299 | K77: Urgent operational requirement!
A78: PO-2024-2151 | B78: 45285 | C78: IT Operations | D78: Hardware Procurement | E78: Prime Space Realty | F78: 357000.42 | G78: GL-500200 | H78: 0% | I78: APPROVED | J78: INV-8453 | K78: Urgent operational requirement!
A79: PO-2024-2153 | B79: 45668 | C79: IT Operations | D79: Software Licenses | E79: CloudSaaS Corp | F79: 142312.2 | G79: GL-600300 | H79: 12% | I79: APPROVED | J79: INV-7887 | K79: System Auto-Generated
A80: PO-2024-2155 | B80: 45759 | C80: IT Operations | D80: Software Licenses | E80: CloudSaaS Corp | F80: 107521.12 | G80: GL-500100 | H80: 0% | I80: APPROVED | J80: INV-4205 | K80: Urgent operational requirement!
A81: PO-2024-2156 | B81: 45645 | C81: IT Operations | D81: Hardware Procurement | E81: CloudSaaS Corp | F81: 146837.72 | G81: GL-500100 | H81: 0% | I81: APPROVED | J81: INV-5123 | K81: Urgent operational requirement!
... A90: PO-2024-2173 | B90: 45734 | C90: Facilities & Ops | D90: Hardware Procurement | E90: GlobalMedia Ads | F90: 220595.19 | G90: GL-500100 | H90: 12% | I90: APPROVED | J90: INV-4596 | K90: System Auto-Generated
A91: PO-2024-2174 | B91: 45811 | C91: Marketing & Sales | D91: Digital Advertising | E91: Prime Space Realty | F91: 109049.84 | G91: GL-600300 | H91: 12% | I91: APPROVED | K91: System Auto-Generated
A92: PO-2024-2175 | B92: 45170 | C92: Unassigned | D92: Office Supplies | E92: GlobalMedia Ads | F92: 164574.19 | G92: GL-500200 | H92: 0% | I92: APPROVED | J92: INV-9228 | K92: System Auto-Generated
A93: PO-2024-2177 | B93: 45126 | C93: Facilities & Ops | D93: Office Rent | E93: PaperCorp Supplies | F93: 50906.8 | G93: GL-500200 | H93: 12% | I93: APPROVED | J93: INV-6119 | K93: System Auto-Generated
A94: PO-2024-2180 | B94: 45414 | C94: IT Operations | D94: Travel & Entertainment | E94: GlobalMedia Ads | F94: 130342.57 | G94: GL-500200 | H94: 12% | I94: APPROVED | J94: INV-7803 | K94: System Auto-Generated
A95: PO-2024-2181 | B95: 45073 | C95: IT Operations | D95: Cloud Infrastructure | E95: Prime Space Realty | F95: 118652.49 | G95: GL-500100 | H95: 0% | I95: APPROVED | J95: INV-6763 | K95: System Auto-Generated
A96: PO-2024-2183 | B96: 45201 | C96: Facilities & Ops | D96: Software Licenses | E96: CloudSaaS Corp | F96: 148411.57 | G96: GL-500200 | H96: 12% | I96: APPROVED | J96: INV-5345 | K96: System Auto-Generated
A97: PO-2024-2186 | B97: 45595 | C97: HR & Admin | D97: Hardware Procurement | E97: GlobalMedia Ads | F97: 111978.49 | G97: GL-500200 | H97: 12% | I97: APPROVED | J97: INV-8967 | K97: System Auto-Generated
A98: PO-2024-2187 | B98: 45702 | C98: HR & Admin | D98: Cloud Infrastructure | E98: Prime Space Realty | F98: 217640.56 | G98: GL-500200 | H98: 12% | I98: APPROVED | J98: INV-6230 | K98: System Auto-Generated
A99: PO-2024-2189 | B99: 44974 | C99: Facilities & Ops | D99: Office Supplies | E99: GlobalMedia Ads | F99: 38054.44 | G99: GL-600300 | H99: 12% | I99: APPROVED | J99: INV-6016 | K99: System Auto-Generated
A100: PO-2024-2194 | B100: 45942 | C100: Marketing & Sales | D100: Office Rent | E100: GlobalMedia Ads | F100: 179359.66 | G100: GL-500200 | H100: 12% | I100: APPROVED | J100: INV-4104 | K100: System Auto-Generated
A101: PO-2024-2195 | B101: 45476 | C101: IT Operations | D101: Cloud Infrastructure | E101: Tech Distributors | G101: GL-500200 | H101: 12% | I101: APPROVED | J101: INV-9122 | K101: System Auto-Generated
A102: PO-2024-2200 | B102: 45335 | C102: Unassigned | D102: Office Rent | E102: GlobalMedia Ads | F102: 14135.02 | G102: GL-500100 | H102: 12% | I102: APPROVED | J102: INV-5128 | K102: System Auto-Generated
A103: PO-2024-2202 | B103: 45649 | C103: Facilities & Ops | D103: Office Supplies | E103: CloudSaaS Corp | F103: 15072.07 | G103: GL-500200 | H103: 12% | I103: APPROVED | J103: INV-8348 | K103: System Auto-Generated
A104: PO-2024-2207 | B104: 45347 | C104: Facilities & Ops | D104: Software Licenses | E104: GlobalMedia Ads | F104: 197858.25 | G104: GL-500100 | H104: 12% | I104: APPROVED | J104: INV-5693 | K104: System Auto-Generated
A105: PO-2024-2209 | B105: 45273 | C105: Facilities & Ops | D105: Office Rent | E105: Paper Corp | F105: 27156.99 | G105: GL-500100 | H105: 12% | I105: APPROVED | J105: INV-6441 | K105: Urgent operational requirement!
A106: PO-2024-2211 | B106: 45621 | C106: IT Operations | D106: Hardware Procurement | E106: GlobalMedia Ads | F106: 267476.75 | G106: GL-600300 | H106: 12% | I106: APPROVED | J106: INV-4397 | K106: Urgent operational requirement!
A107: PO-2024-2212 | B107: 45666 | C107: Marketing & Sales | D107: Office Supplies | E107: PaperCorp Supplies | F107: 93324.05 | G107: GL-600300 | H107: 12% | I107: APPROVED | K107: System Auto-Generated
A108: PO-2024-2213 | B108: 45973 | C108: Marketing & Sales | D108: Software Licenses | E108: CloudSaaS Corp | F108: 249802.38 | G108: GL-600300 | H108: 0% | I108: APPROVED | J108: INV-6988 | K108: System Auto-Generated
A109: PO-2024-2214 | B109: 45847 | C109: Facilities & Ops | D109: Hardware Procurement | E109: TechDistributors Inc | F109: 56137.66 | G109: GL-500200 | H109: 12% | I109: APPROVED | J109: INV-5222 | K109: Urgent operational requirement!
...

Sheet Dim_Budgets
A1: Fiscal_Year | B1: Department | C1: Allocated_Budget_PHP
A2: 2023 | B2: IT Operations | C2: 6500000
A3: 2023 | B3: Marketing & Sales | C3: 5200000
A4: 2023 | B4: HR & Admin | C4: 4100000
A5: 2023 | B5: Facilities & Ops | C5: 5800000
A6: 2024 | B6: IT Operations | C6: 6890000
A7: 2024 | B7: Marketing & Sales | C7: 5510000
A8: 2024 | B8: HR & Admin | C8: 4340000
A9: 2024 | B9: Facilities & Ops | C9: 6140000
A10: 2025 | B10: IT Operations | C10: 7300000
A11: 2025 | B11: Marketing & Sales | C11: 5840000
A12: 2025 | B12: HR & Admin | C12: 4600000
A13: 2025 | B13: Facilities & Ops | C13: 6500000

Sheet Sheet1
A1: Row Labels | B1: Sum of RAW_AMOUNT
A2: <05/01/2023 | D2: Budget | E2: Variance
A3: 2023 | B3: 23139384 | D3: =SUM(D4:D8) -> 21600000 | I3: % | K3: Dept | L3: Total Budget | M3: Total Expenditure | N3: Variance | O3: Variance % | P3: Overspend | Q3: Variance
A4: Facilities & Ops | B4: 6190664.8 | C4: 6190664.8 | D4: =_xlfn.XLOOKUP(A4,Dim_Budgets!$B$2:$B$5,Dim_Budgets!$C$2:$C$5) -> 5800000 | E4: =D4-C4 -> -390664.82 | G4: Total Variance | H4: =SUM(E4:E20) -> -9344600.1 | I4: =H4/D21 -> -0.13598079 | K4: Facilities & Ops | L4: =SUMIFS($D$4:$D$20,$A$4:$A$20,K4) -> 18440000 | M4: =SUMIFS($B$4:$B$20,$A$4:$A$20,K4) -> 22656061 | N4: =L4-M4 -> -4216061.2 | O4: =N4/L4 -> -0.22863672 | P4: =SUMIFS($E$4:$E$20,$A$4:$A$20,K4,$E$4:$E$20,"<0") -> -4216061.2 | Q4: =P4/L4 -> -0.22863672
A5: HR & Admin | B5: 2251691.5 | C5: 2251691.5 | D5: =_xlfn.XLOOKUP(A5,Dim_Budgets!$B$2:$B$5,Dim_Budgets!$C$2:$C$5) -> 4100000 | E5: =D5-C5 -> 1848308.5 | G5: Overspend Total | H5: =SUMIF(E4:E20,"<0") -> -13135835 | I5: =H5/D21 -> -0.1911501 | K5: HR & Admin | L5: =SUMIFS($D$4:$D$20,$A$4:$A$20,K5) -> 13040000 | M5: =SUMIFS($B$4:$B$20,$A$4:$A$20,K5) -> 9550675.7 | N5: =L5-M5 -> 3489324.3 | O5: =N5/L5 -> 0.26758622 | P5: =SUMIFS($E$4:$E$20,$A$4:$A$20,K5,$E$4:$E$20,"<0") -> 0 | Q5: =P5/L5 -> 0
A6: IT Operations | B6: 7988971.4 | C6: 7988971.4 | D6: =_xlfn.XLOOKUP(A6,Dim_Budgets!$B$2:$B$5,Dim_Budgets!$C$2:$C$5) -> 6500000 | E6: =D6-C6 -> -1488971.4 | G6: Approved Budget | H6: =D21 -> 68720000 | K6: IT Operations | L6: =SUMIFS($D$4:$D$20,$A$4:$A$20,K6) -> 20690000 | M6: =SUMIFS($B$4:$B$20,$A$4:$A$20,K6) -> 21877061 | N6: =L6-M6 -> -1187061.1 | O6: =N6/L6 -> -0.057373666 | P6: =SUMIFS($E$4:$E$20,$A$4:$A$20,K6,$E$4:$E$20,"<0") -> -1488971.4 | Q6: =P6/L6 -> -0.071965754
A7: Marketing & Sales | B7: 5594418.6 | C7: 5594418.6 | D7: =_xlfn.XLOOKUP(A7,Dim_Budgets!$B$2:$B$5,Dim_Budgets!$C$2:$C$5) -> 5200000 | E7: =D7-C7 -> -394418.6 | G7: Total Expenditures | H7: =GETPIVOTDATA("RAW_AMOUNT",$A$1) -> 78064600 | K7: Marketing & Sales | L7: =SUMIFS($D$4:$D$20,$A$4:$A$20,K7) -> 16550000 | M7: =SUMIFS($B$4:$B$20,$A$4:$A$20,K7) -> 21019775 | N7: =L7-M7 -> -4469775.4 | O7: =N7/L7 -> -0.27007707 | P7: =SUMIFS($E$4:$E$20,$A$4:$A$20,K7,$E$4:$E$20,"<0") -> -4469775.4 | Q7: =P7/L7 -> -0.27007707
A8: Unassigned | B8: 1113637.3 | C8: 1113637.3 | E8: =D8-C8 -> -1113637.3 | K8: Unassigned | L8: =SUMIFS($D$4:$D$20,$A$4:$A$20,K8) -> 0 | M8: =SUMIFS($B$4:$B$20,$A$4:$A$20,K8) -> 2961026.7 | N8: =L8-M8 -> -2961026.7 | O8: =M8/L8 -> #DIV/0! | P8: =SUMIFS($E$4:$E$20,$A$4:$A$20,K8,$E$4:$E$20,"<0") -> -2961026.7 | Q8: =P8/L8 -> #DIV/0!
A9: 2024 | B9: 28451017 | D9: =SUM(D10:D14) -> 22880000
A10: Facilities & Ops | B10: 8618590.6 | C10: 8618590.6 | D10: =_xlfn.XLOOKUP(A10,Dim_Budgets!$B$6:$B$9,Dim_Budgets!$C$6:$C$9) -> 6140000 | E10: =D10-C10 -> -2478590.6
A11: HR & Admin | B11: 3493418.2 | C11: 3493418.2 | D11: =_xlfn.XLOOKUP(A11,Dim_Budgets!$B$6:$B$9,Dim_Budgets!$C$6:$C$9) -> 4340000 | E11: =D11-C11 -> 846581.75
A12: IT Operations | B12: 6640728.1 | C12: 6640728.1 | D12: =_xlfn.XLOOKUP(A12,Dim_Budgets!$B$6:$B$9,Dim_Budgets!$C$6:$C$9) -> 6890000 | E12: =D12-C12 -> 249271.89
A13: Marketing & Sales | B13: 9007624.5 | C13: 9007624.5 | D13: =_xlfn.XLOOKUP(A13,Dim_Budgets!$B$6:$B$9,Dim_Budgets!$C$6:$C$9) -> 5510000 | E13: =D13-C13 -> -3497624.5
A14: Unassigned | B14: 690655.09 | C14: 690655.09 | E14: =D14-C14 -> -690655.09
A15: 2025 | B15: 26474200 | D15: =SUM(D16:D20) -> 24240000 | G15: Budget | H15: Actual Spend
A16: Facilities & Ops | B16: 7846805.7 | C16: 7846805.7 | D16: =_xlfn.XLOOKUP(A16,Dim_Budgets!$B$10:$B$13,Dim_Budgets!$C$10:$C$13) -> 6500000 | E16: =D16-C16 -> -1346805.7 | G16: 21600000 | H16: 23139384
A17: HR & Admin | B17: 3805565.9 | C17: 3805565.9 | D17: =_xlfn.XLOOKUP(A17,Dim_Budgets!$B$10:$B$13,Dim_Budgets!$C$10:$C$13) -> 4600000 | E17: =D17-C17 -> 794434.15 | G17: 22880000 | H17: 28451017
A18: IT Operations | B18: 7247361.6 | C18: 7247361.6 | D18: =_xlfn.XLOOKUP(A18,Dim_Budgets!$B$10:$B$13,Dim_Budgets!$C$10:$C$13) -> 7300000 | E18: =D18-C18 -> 52638.4 | G18: 24240000 | H18: 26474200
A19: Marketing & Sales | B19: 6417732.4 | C19: 6417732.4 | D19: =_xlfn.XLOOKUP(A19,Dim_Budgets!$B$10:$B$13,Dim_Budgets!$C$10:$C$13) -> 5840000 | E19: =D19-C19 -> -577732.36
A20: Unassigned | B20: 1156734.3 | C20: 1156734.3 | E20: =D20-C20 -> -1156734.3
A21: Grand Total | B21: 78064600 | C21: =SUM(C4:C20) -> 78064600 | D21: =SUM(D3,D9,D15) -> 68720000 | E21: =D21-GETPIVOTDATA("RAW_AMOUNT",$A$1) -> -9344600.1
